<string_table>
    <string id="ui_mcm_werasik2aa_show_marks">
		<text>Show player marks</text>
	</string>
    <string id="ui_mcm_werasik2aa_show_name">
		<text>Show nickname near mark</text>
	</string>
    <string id="ui_mcm_werasik2aa_clear_inv">
		<text>Clear inventory after death</text>
	</string>
	<string id="ui_mcm_werasik2aa_drop_inv">
		<text>Drop items after death</text>
	</string>
    <string id="ui_mcm_werasik2aa_sync_given_i">
		<text>Sync given items of reward from task</text>
	</string>
    <string id="ui_mcm_werasik2aa_max_players">
		<text>[Server] Max players</text>
	</string>
	<string id="ui_mcm_werasik2aa_friendly_fire">
		<text>[╤хЁтхЁ] Friendly fire</text>
	</string>
	<string id="ui_radmp_title">
		<text>Anomaly Together 2.0</text>
	</string>
    <string id="ui_mcm_menu_werasik2aa">
		<text>Anomaly Together</text>
	</string>
	<string id="ui_mcm_werasik2aa_p2p_peer_chat">
		<text>Open chat keybind</text>
	</string>
	<string id="st_cap_check_warfarem">
		<text>Warfare (BETA)</text>
	</string>

	<string id="ui_mm_host_port">
		<text>Server IP</text>
	</string>
    <string id="ui_mm_user_name">
		<text>Nickname:</text>
	</string>
	<string id="ui_mm_newgames">
		<text>New profile</text>
	</string>
	<string id="ui_mm_createserver">
		<text>Load profile</text>
	</string>
	<string id="ui_st_connecting_to_server">
		<text>Please wait, connecting to server...</text>
	</string>
	<string id="ui_cons_failed">
		<text>Failed to connect to the server, the server did not send packets in the required time. Timed Out</text>
	</string>
	<string id="ui_cons_failed_kick">
		<text>You have been kicked!</text>
	</string>
	<string id="ui_mm_resc_con_game">
		<text>Resurrect</text>
	</string>
	<string id="ui_mm_conn_to_game">
		<text>Connect by IP</text>
	</string>
	<string id="ui_mm_load_game">
		<text>Select profile</text>
	</string>
	<string id="ui_mm_ads_game">
		<text>╥хєяюффхЁцър т Discord</text>
	</string>
</string_table>